openbb_regulators/__init__.py
openbb_regulators/cftc/__init__.py
openbb_regulators/cftc/cftc_router.py
openbb_regulators/regulators_router.py
openbb_regulators/sec/__init__.py
openbb_regulators/sec/sec_router.py
openbb_regulators-1.4.2.dist-info/METADATA
openbb_regulators-1.4.2.dist-info/WHEEL
openbb_regulators-1.4.2.dist-info/entry_points.txt
openbb_regulators-1.4.2.dist-info/RECORD
